README.md
setup.py
case_convert/__init__.py
case_convert/general_words.txt
case_convert/main.py
case_convert.egg-info/PKG-INFO
case_convert.egg-info/SOURCES.txt
case_convert.egg-info/dependency_links.txt
case_convert.egg-info/top_level.txt