Metadata-Version: 2.1
Name: case-convert
Version: 1.0.13
Summary: Cross library to convert case with permissive input
Home-page: https://gitlab.com/olive007/case-convert
Author: SECRET Olivier
Author-email: pypi-package-case_convert@devo.live
License: UNKNOWN
Platform: UNKNOWN
Classifier: Programming Language :: Python :: 3
Classifier: License :: OSI Approved :: GNU Lesser General Public License v3 or later (LGPLv3+)
Classifier: Operating System :: OS Independent
